MANIFEST.in
README
setup.py
rb_oauth/__init__.py
rb_oauth/_backend.py
rb_oauth/_registry.py
rb_oauth/defaults.py
rb_oauth/extension.py
rb_oauth/urls.py
rb_oauth/views.py
rb_oauth.egg-info/PKG-INFO
rb_oauth.egg-info/SOURCES.txt
rb_oauth.egg-info/dependency_links.txt
rb_oauth.egg-info/entry_points.txt
rb_oauth.egg-info/not-zip-safe
rb_oauth.egg-info/top_level.txt
rb_oauth/providers/__init__.py
rb_oauth/providers/_depend.py
rb_oauth/providers/accounts.py
rb_oauth/providers/base.py
rb_oauth/providers/github.py
rb_oauth/templates/providers.html