Metadata-Version: 1.0
Name: rb-oauth
Version: 0.3
Summary: This reviewboard extension allows authentication via OAuth.
Home-page: https://bitbucket.org/ericsnowcurrently/rb_oauth_extension
Author: Eric Snow
Author-email: UNKNOWN
License: New BSD License
Platform: UNKNOWN
